{
  "$schema": "https://playground.wordpress.net/blueprint-schema.json",
  "landingPage": "/wp-admin/",
  "login": true,
  "features": {
    "networking": true
  },
  "steps": [
    {
      "step": "installPlugin",
      "options": {
        "activate": true,
        "targetFolderName": "wc-logrono-2025-talk"
      },
      "pluginData": {
        "resource": "git:directory",
        "url": "https://github.com/juanma-wp/wc-logrono-2025-talk",
        "ref": "HEAD",
        "path": "/"
      }
    }
  ]
}
